git_pass/__init__.py
git_pass_helper-0.2.1.dist-info/METADATA
git_pass_helper-0.2.1.dist-info/WHEEL
git_pass_helper-0.2.1.dist-info/entry_points.txt
git_pass_helper-0.2.1.dist-info/top_level.txt
git_pass_helper-0.2.1.dist-info/RECORD
