Metadata-Version: 2.4
Name: git-pass-helper
Version: 0.2.1
Author-email: Louis Burda <dev@sinitax.com>
License-Expression: MIT
Requires-Python: >=3.10
Requires-Dist: dotenv>=0.9.9
